[{"lng": -0.10903, "lat": 51.45358, "delta": 0, "distance": 0}, {"lng": -0.10935, "lat": 51.4537, "delta": 26, "distance": 26}, {"lng": -0.10993, "lat": 51.45393, "delta": 48, "distance": 74}, {"lng": -0.11024, "lat": 51.45404, "delta": 25, "distance": 99}, {"lng": -0.11042, "lat": 51.45411, "delta": 15, "distance": 114}, {"lng": -0.11057, "lat": 51.45415, "delta": 12, "distance": 126}, {"lng": -0.11079, "lat": 51.45423, "delta": 18, "distance": 144}, {"lng": -0.11107, "lat": 51.45431, "delta": 22, "distance": 166}, {"lng": -0.11117, "lat": 51.45435, "delta": 9, "distance": 175}, {"lng": -0.11125, "lat": 51.45437, "delta": 6, "distance": 181}, {"lng": -0.11132, "lat": 51.45438, "delta": 5, "distance": 186}, {"lng": -0.11137, "lat": 51.45437, "delta": 4, "distance": 190}, {"lng": -0.11129, "lat": 51.4542, "delta": 20, "distance": 210}, {"lng": -0.11116, "lat": 51.45396, "delta": 29, "distance": 239}, {"lng": -0.11106, "lat": 51.45378, "delta": 22, "distance": 261}, {"lng": -0.111, "lat": 51.45364, "delta": 17, "distance": 278}, {"lng": -0.11094, "lat": 51.45348, "delta": 19, "distance": 297}, {"lng": -0.11088, "lat": 51.45331, "delta": 20, "distance": 317}, {"lng": -0.11083, "lat": 51.45316, "delta": 18, "distance": 335}, {"lng": -0.11071, "lat": 51.45286, "delta": 35, "distance": 370}, {"lng": -0.11072, "lat": 51.4528, "delta": 7, "distance": 377}, {"lng": -0.11075, "lat": 51.45271, "delta": 11, "distance": 388}, {"lng": -0.11076, "lat": 51.45269, "delta": 3, "distance": 391}, {"lng": -0.1108, "lat": 51.45263, "delta": 8, "distance": 399}, {"lng": -0.11085, "lat": 51.45258, "delta": 7, "distance": 406}, {"lng": -0.11091, "lat": 51.45253, "delta": 7, "distance": 413}, {"lng": -0.1111, "lat": 51.45239, "delta": 21, "distance": 434}, {"lng": -0.11123, "lat": 51.45238, "delta": 10, "distance": 444}, {"lng": -0.11163, "lat": 51.45235, "delta": 28, "distance": 472}, {"lng": -0.11179, "lat": 51.45233, "delta": 12, "distance": 484}, {"lng": -0.11186, "lat": 51.45232, "delta": 5, "distance": 489}, {"lng": -0.11194, "lat": 51.4523, "delta": 6, "distance": 495}, {"lng": -0.11195, "lat": 51.45213, "delta": 19, "distance": 514}, {"lng": -0.11198, "lat": 51.45191, "delta": 25, "distance": 539}, {"lng": -0.11199, "lat": 51.45182, "delta": 11, "distance": 550}, {"lng": -0.11201, "lat": 51.45172, "delta": 12, "distance": 562}, {"lng": -0.11201, "lat": 51.45167, "delta": 6, "distance": 568}, {"lng": -0.11202, "lat": 51.45161, "delta": 7, "distance": 575}, {"lng": -0.11202, "lat": 51.45157, "delta": 5, "distance": 580}, {"lng": -0.11202, "lat": 51.45152, "delta": 6, "distance": 586}, {"lng": -0.11201, "lat": 51.45147, "delta": 6, "distance": 592}, {"lng": -0.11199, "lat": 51.45142, "delta": 6, "distance": 598}, {"lng": -0.11197, "lat": 51.45138, "delta": 5, "distance": 603}, {"lng": -0.11194, "lat": 51.45132, "delta": 7, "distance": 610}, {"lng": -0.11187, "lat": 51.45122, "delta": 13, "distance": 623}, {"lng": -0.11181, "lat": 51.45115, "delta": 9, "distance": 632}, {"lng": -0.11174, "lat": 51.45109, "delta": 9, "distance": 641}, {"lng": -0.11171, "lat": 51.45107, "delta": 4, "distance": 645}, {"lng": -0.11151, "lat": 51.45088, "delta": 26, "distance": 671}, {"lng": -0.11142, "lat": 51.45079, "delta": 12, "distance": 683}, {"lng": -0.1111, "lat": 51.45042, "delta": 47, "distance": 730}, {"lng": -0.11103, "lat": 51.45032, "delta": 13, "distance": 743}, {"lng": -0.11094, "lat": 51.45018, "delta": 17, "distance": 760}, {"lng": -0.11091, "lat": 51.45006, "delta": 14, "distance": 774}, {"lng": -0.11088, "lat": 51.44991, "delta": 17, "distance": 791}, {"lng": -0.11094, "lat": 51.44983, "delta": 10, "distance": 801}, {"lng": -0.11106, "lat": 51.44968, "delta": 19, "distance": 820}, {"lng": -0.11111, "lat": 51.44964, "delta": 6, "distance": 826}, {"lng": -0.11131, "lat": 51.44941, "delta": 30, "distance": 856}, {"lng": -0.11138, "lat": 51.44931, "delta": 13, "distance": 869}, {"lng": -0.11141, "lat": 51.44925, "delta": 7, "distance": 876}, {"lng": -0.11147, "lat": 51.44916, "delta": 11, "distance": 887}, {"lng": -0.1115, "lat": 51.44906, "delta": 12, "distance": 899}, {"lng": -0.11152, "lat": 51.44894, "delta": 14, "distance": 913}, {"lng": -0.11152, "lat": 51.44881, "delta": 15, "distance": 928}, {"lng": -0.11149, "lat": 51.44864, "delta": 20, "distance": 948}, {"lng": -0.11147, "lat": 51.44852, "delta": 14, "distance": 962}, {"lng": -0.11145, "lat": 51.44845, "delta": 8, "distance": 970}, {"lng": -0.11143, "lat": 51.44839, "delta": 7, "distance": 977}, {"lng": -0.1114, "lat": 51.44824, "delta": 17, "distance": 994}, {"lng": -0.11136, "lat": 51.44814, "delta": 12, "distance": 1006}, {"lng": -0.11133, "lat": 51.44807, "delta": 9, "distance": 1015}, {"lng": -0.11126, "lat": 51.44793, "delta": 17, "distance": 1032}, {"lng": -0.11114, "lat": 51.44776, "delta": 21, "distance": 1053}, {"lng": -0.11096, "lat": 51.44754, "delta": 28, "distance": 1081}, {"lng": -0.11082, "lat": 51.44737, "delta": 22, "distance": 1103}, {"lng": -0.1107, "lat": 51.44721, "delta": 20, "distance": 1123}, {"lng": -0.11066, "lat": 51.44709, "delta": 14, "distance": 1137}, {"lng": -0.11062, "lat": 51.44699, "delta": 12, "distance": 1149}, {"lng": -0.1106, "lat": 51.44688, "delta": 13, "distance": 1162}, {"lng": -0.11056, "lat": 51.44673, "delta": 17, "distance": 1179}, {"lng": -0.11052, "lat": 51.44658, "delta": 17, "distance": 1196}, {"lng": -0.11042, "lat": 51.44635, "delta": 27, "distance": 1223}, {"lng": -0.11038, "lat": 51.44629, "delta": 8, "distance": 1231}, {"lng": -0.11033, "lat": 51.44622, "delta": 9, "distance": 1240}, {"lng": -0.11031, "lat": 51.44619, "delta": 4, "distance": 1244}, {"lng": -0.11027, "lat": 51.44617, "delta": 4, "distance": 1248}, {"lng": -0.11023, "lat": 51.44614, "delta": 5, "distance": 1253}, {"lng": -0.11019, "lat": 51.44612, "delta": 4, "distance": 1257}, {"lng": -0.11015, "lat": 51.44611, "delta": 3, "distance": 1260}, {"lng": -0.11007, "lat": 51.4461, "delta": 6, "distance": 1266}, {"lng": -0.10992, "lat": 51.44608, "delta": 11, "distance": 1277}, {"lng": -0.10978, "lat": 51.44607, "delta": 10, "distance": 1287}, {"lng": -0.10962, "lat": 51.44607, "delta": 12, "distance": 1299}, {"lng": -0.10945, "lat": 51.44608, "delta": 12, "distance": 1311}, {"lng": -0.10919, "lat": 51.44612, "delta": 19, "distance": 1330}, {"lng": -0.10891, "lat": 51.44617, "delta": 21, "distance": 1351}, {"lng": -0.10868, "lat": 51.44622, "delta": 17, "distance": 1368}, {"lng": -0.1077, "lat": 51.44641, "delta": 72, "distance": 1440}, {"lng": -0.10738, "lat": 51.44646, "delta": 23, "distance": 1463}, {"lng": -0.10717, "lat": 51.44649, "delta": 15, "distance": 1478}, {"lng": -0.10692, "lat": 51.44652, "delta": 18, "distance": 1496}, {"lng": -0.10673, "lat": 51.44653, "delta": 14, "distance": 1510}, {"lng": -0.1066, "lat": 51.44655, "delta": 10, "distance": 1520}, {"lng": -0.1065, "lat": 51.44657, "delta": 8, "distance": 1528}, {"lng": -0.1064, "lat": 51.44661, "delta": 9, "distance": 1537}, {"lng": -0.10629, "lat": 51.44666, "delta": 10, "distance": 1547}, {"lng": -0.10607, "lat": 51.44674, "delta": 18, "distance": 1565}, {"lng": -0.10602, "lat": 51.44675, "delta": 4, "distance": 1569}, {"lng": -0.10595, "lat": 51.44677, "delta": 6, "distance": 1575}, {"lng": -0.10588, "lat": 51.44677, "delta": 5, "distance": 1580}, {"lng": -0.10579, "lat": 51.44677, "delta": 7, "distance": 1587}, {"lng": -0.1056, "lat": 51.44678, "delta": 14, "distance": 1601}, {"lng": -0.10546, "lat": 51.44678, "delta": 10, "distance": 1611}, {"lng": -0.10526, "lat": 51.44679, "delta": 14, "distance": 1625}, {"lng": -0.10507, "lat": 51.44682, "delta": 14, "distance": 1639}, {"lng": -0.1049, "lat": 51.44685, "delta": 13, "distance": 1652}, {"lng": -0.10481, "lat": 51.44688, "delta": 8, "distance": 1660}, {"lng": -0.10477, "lat": 51.4469, "delta": 4, "distance": 1664}, {"lng": -0.10473, "lat": 51.44693, "delta": 5, "distance": 1669}, {"lng": -0.10469, "lat": 51.447, "delta": 9, "distance": 1678}, {"lng": -0.10465, "lat": 51.44712, "delta": 14, "distance": 1692}, {"lng": -0.10459, "lat": 51.44727, "delta": 18, "distance": 1710}, {"lng": -0.10455, "lat": 51.44738, "delta": 13, "distance": 1723}, {"lng": -0.10442, "lat": 51.4476, "delta": 27, "distance": 1750}, {"lng": -0.10426, "lat": 51.44786, "delta": 31, "distance": 1781}, {"lng": -0.10417, "lat": 51.448, "delta": 17, "distance": 1798}, {"lng": -0.10411, "lat": 51.44807, "delta": 9, "distance": 1807}, {"lng": -0.10404, "lat": 51.44815, "delta": 11, "distance": 1818}, {"lng": -0.10399, "lat": 51.4482, "delta": 7, "distance": 1825}, {"lng": -0.10372, "lat": 51.44842, "delta": 31, "distance": 1856}, {"lng": -0.10358, "lat": 51.44853, "delta": 16, "distance": 1872}, {"lng": -0.10345, "lat": 51.44863, "delta": 15, "distance": 1887}, {"lng": -0.10324, "lat": 51.44882, "delta": 26, "distance": 1913}, {"lng": -0.10317, "lat": 51.44888, "delta": 9, "distance": 1922}, {"lng": -0.10309, "lat": 51.44896, "delta": 11, "distance": 1933}, {"lng": -0.10291, "lat": 51.44918, "delta": 28, "distance": 1961}, {"lng": -0.10279, "lat": 51.44934, "delta": 20, "distance": 1981}, {"lng": -0.10255, "lat": 51.44969, "delta": 43, "distance": 2024}, {"lng": -0.10242, "lat": 51.4499, "delta": 26, "distance": 2050}, {"lng": -0.10229, "lat": 51.45012, "delta": 27, "distance": 2077}, {"lng": -0.10218, "lat": 51.45034, "delta": 26, "distance": 2103}, {"lng": -0.10209, "lat": 51.45056, "delta": 26, "distance": 2129}, {"lng": -0.10196, "lat": 51.45091, "delta": 40, "distance": 2169}, {"lng": -0.1019, "lat": 51.4511, "delta": 22, "distance": 2191}, {"lng": -0.10187, "lat": 51.45128, "delta": 21, "distance": 2212}, {"lng": -0.10184, "lat": 51.45149, "delta": 24, "distance": 2236}, {"lng": -0.10182, "lat": 51.45181, "delta": 36, "distance": 2272}, {"lng": -0.10182, "lat": 51.45191, "delta": 12, "distance": 2284}, {"lng": -0.10184, "lat": 51.45196, "delta": 6, "distance": 2290}, {"lng": -0.10193, "lat": 51.45202, "delta": 10, "distance": 2300}, {"lng": -0.10202, "lat": 51.45208, "delta": 10, "distance": 2310}, {"lng": -0.10206, "lat": 51.45211, "delta": 5, "distance": 2315}, {"lng": -0.10208, "lat": 51.45211, "delta": 2, "distance": 2317}, {"lng": -0.10211, "lat": 51.45211, "delta": 3, "distance": 2320}, {"lng": -0.10236, "lat": 51.45211, "delta": 18, "distance": 2338}, {"lng": -0.10251, "lat": 51.45212, "delta": 11, "distance": 2349}, {"lng": -0.10265, "lat": 51.45212, "delta": 10, "distance": 2359}, {"lng": -0.10272, "lat": 51.45213, "delta": 5, "distance": 2364}, {"lng": -0.10286, "lat": 51.45214, "delta": 10, "distance": 2374}, {"lng": -0.10295, "lat": 51.45216, "delta": 7, "distance": 2381}, {"lng": -0.10304, "lat": 51.45218, "delta": 7, "distance": 2388}, {"lng": -0.10319, "lat": 51.45222, "delta": 12, "distance": 2400}, {"lng": -0.1034, "lat": 51.45228, "delta": 17, "distance": 2417}, {"lng": -0.10357, "lat": 51.45235, "delta": 15, "distance": 2432}, {"lng": -0.10382, "lat": 51.45246, "delta": 22, "distance": 2454}, {"lng": -0.10397, "lat": 51.45252, "delta": 13, "distance": 2467}, {"lng": -0.10407, "lat": 51.45255, "delta": 8, "distance": 2475}, {"lng": -0.1042, "lat": 51.45259, "delta": 11, "distance": 2486}, {"lng": -0.10428, "lat": 51.45261, "delta": 6, "distance": 2492}, {"lng": -0.10441, "lat": 51.45264, "delta": 10, "distance": 2502}, {"lng": -0.10449, "lat": 51.45266, "delta": 6, "distance": 2508}, {"lng": -0.10466, "lat": 51.45269, "delta": 13, "distance": 2521}, {"lng": -0.10484, "lat": 51.45271, "delta": 13, "distance": 2534}, {"lng": -0.10502, "lat": 51.45273, "delta": 13, "distance": 2547}, {"lng": -0.10529, "lat": 51.45275, "delta": 19, "distance": 2566}, {"lng": -0.10534, "lat": 51.45272, "delta": 5, "distance": 2571}, {"lng": -0.10546, "lat": 51.45264, "delta": 13, "distance": 2584}, {"lng": -0.10552, "lat": 51.45259, "delta": 7, "distance": 2591}, {"lng": -0.10555, "lat": 51.45258, "delta": 3, "distance": 2594}, {"lng": -0.10561, "lat": 51.45255, "delta": 6, "distance": 2600}, {"lng": -0.10569, "lat": 51.45253, "delta": 6, "distance": 2606}, {"lng": -0.10605, "lat": 51.4525, "delta": 26, "distance": 2632}, {"lng": -0.10651, "lat": 51.45263, "delta": 35, "distance": 2667}, {"lng": -0.10673, "lat": 51.4527, "delta": 18, "distance": 2685}, {"lng": -0.10696, "lat": 51.45277, "delta": 18, "distance": 2703}, {"lng": -0.10726, "lat": 51.45287, "delta": 24, "distance": 2727}, {"lng": -0.10732, "lat": 51.45282, "delta": 7, "distance": 2734}, {"lng": -0.10795, "lat": 51.4524, "delta": 64, "distance": 2798}, {"lng": -0.10862, "lat": 51.45197, "delta": 67, "distance": 2865}, {"lng": -0.10877, "lat": 51.45187, "delta": 16, "distance": 2881}, {"lng": -0.1089, "lat": 51.45178, "delta": 14, "distance": 2895}, {"lng": -0.10917, "lat": 51.45162, "delta": 26, "distance": 2921}, {"lng": -0.10929, "lat": 51.45155, "delta": 12, "distance": 2933}, {"lng": -0.10933, "lat": 51.45158, "delta": 5, "distance": 2938}, {"lng": -0.1094, "lat": 51.45157, "delta": 5, "distance": 2943}, {"lng": -0.11009, "lat": 51.45136, "delta": 54, "distance": 2997}, {"lng": -0.11074, "lat": 51.45116, "delta": 51, "distance": 3048}, {"lng": -0.11089, "lat": 51.45112, "delta": 12, "distance": 3060}, {"lng": -0.11097, "lat": 51.4511, "delta": 6, "distance": 3066}, {"lng": -0.11104, "lat": 51.45109, "delta": 5, "distance": 3071}, {"lng": -0.11111, "lat": 51.45109, "delta": 5, "distance": 3076}, {"lng": -0.11117, "lat": 51.45109, "delta": 5, "distance": 3081}, {"lng": -0.11133, "lat": 51.45112, "delta": 12, "distance": 3093}, {"lng": -0.11141, "lat": 51.45113, "delta": 6, "distance": 3099}, {"lng": -0.11143, "lat": 51.45113, "delta": 2, "distance": 3101}, {"lng": -0.11148, "lat": 51.45113, "delta": 4, "distance": 3105}, {"lng": -0.11153, "lat": 51.45112, "delta": 4, "distance": 3109}, {"lng": -0.11166, "lat": 51.45109, "delta": 10, "distance": 3119}, {"lng": -0.11171, "lat": 51.45107, "delta": 5, "distance": 3124}, {"lng": -0.11165, "lat": 51.45101, "delta": 8, "distance": 3132}]