[{"lng": 152.170043, "lat": -32.747832, "delta": 0, "distance": 0}, {"lng": 152.170129, "lat": -32.746966, "delta": 97, "distance": 97}, {"lng": 152.169914, "lat": -32.746533, "delta": 53, "distance": 150}, {"lng": 152.169871, "lat": -32.74563, "delta": 101, "distance": 251}, {"lng": 152.169828, "lat": -32.744728, "delta": 101, "distance": 352}, {"lng": 152.170086, "lat": -32.74397, "delta": 88, "distance": 440}, {"lng": 152.170601, "lat": -32.74314, "delta": 105, "distance": 545}, {"lng": 152.170687, "lat": -32.742743, "delta": 45, "distance": 590}, {"lng": 152.17133, "lat": -32.741949, "delta": 107, "distance": 697}, {"lng": 152.172318, "lat": -32.740577, "delta": 179, "distance": 876}, {"lng": 152.172661, "lat": -32.739999, "delta": 72, "distance": 948}, {"lng": 152.17287500000003, "lat": -32.738447, "delta": 174, "distance": 1122}, {"lng": 152.17313300000004, "lat": -32.736823, "delta": 183, "distance": 1305}, {"lng": 152.17339, "lat": -32.735992, "delta": 96, "distance": 1401}, {"lng": 152.17339, "lat": -32.734801, "delta": 133, "distance": 1534}, {"lng": 152.173305, "lat": -32.734115, "delta": 77, "distance": 1611}, {"lng": 152.171845, "lat": -32.732058, "delta": 267, "distance": 1878}]