[{"lng": -0.711418, "lat": 51.512021, "delta": 0, "distance": 0}, {"lng": -0.710817, "lat": 51.510189, "delta": 208, "distance": 208}, {"lng": -0.710866, "lat": 51.509741, "delta": 50, "distance": 258}, {"lng": -0.710973, "lat": 51.509303, "delta": 50, "distance": 308}, {"lng": -0.711118, "lat": 51.508763, "delta": 61, "distance": 369}, {"lng": -0.711252, "lat": 51.508579, "delta": 23, "distance": 392}, {"lng": -0.711107, "lat": 51.508609, "delta": 11, "distance": 403}, {"lng": -0.711005, "lat": 51.508586, "delta": 8, "distance": 411}, {"lng": -0.710753, "lat": 51.508479, "delta": 22, "distance": 433}, {"lng": -0.710565, "lat": 51.508435, "delta": 14, "distance": 447}, {"lng": -0.710372, "lat": 51.508485, "delta": 15, "distance": 462}, {"lng": -0.71019, "lat": 51.508649, "delta": 23, "distance": 485}, {"lng": -0.71027, "lat": 51.509003, "delta": 40, "distance": 525}, {"lng": -0.710404, "lat": 51.509794, "delta": 89, "distance": 614}, {"lng": -0.711048, "lat": 51.512198, "delta": 272, "distance": 886}, {"lng": -0.711402, "lat": 51.513537, "delta": 151, "distance": 1037}, {"lng": -0.712008, "lat": 51.51585, "delta": 261, "distance": 1298}, {"lng": -0.711778, "lat": 51.515934, "delta": 19, "distance": 1317}, {"lng": -0.711494, "lat": 51.516007, "delta": 22, "distance": 1339}, {"lng": -0.71115, "lat": 51.516041, "delta": 25, "distance": 1364}, {"lng": -0.710565, "lat": 51.51606, "delta": 41, "distance": 1405}, {"lng": -0.710453, "lat": 51.515997, "delta": 11, "distance": 1416}, {"lng": -0.710238, "lat": 51.515516, "delta": 56, "distance": 1472}, {"lng": -0.709718, "lat": 51.514508, "delta": 118, "distance": 1590}, {"lng": -0.708811, "lat": 51.512772, "delta": 203, "distance": 1793}, {"lng": -0.708827, "lat": 51.512592, "delta": 21, "distance": 1814}, {"lng": -0.708747, "lat": 51.512452, "delta": 17, "distance": 1831}, {"lng": -0.708645, "lat": 51.512258, "delta": 23, "distance": 1854}, {"lng": -0.707862, "lat": 51.510709, "delta": 181, "distance": 2035}, {"lng": -0.707894, "lat": 51.510352, "delta": 40, "distance": 2075}, {"lng": -0.707974, "lat": 51.510255, "delta": 13, "distance": 2088}, {"lng": -0.708194, "lat": 51.510131, "delta": 21, "distance": 2109}, {"lng": -0.708532, "lat": 51.509914, "delta": 34, "distance": 2143}, {"lng": -0.708752, "lat": 51.509824, "delta": 19, "distance": 2162}, {"lng": -0.709594, "lat": 51.509103, "delta": 100, "distance": 2262}, {"lng": -0.710163, "lat": 51.508659, "delta": 64, "distance": 2326}, {"lng": -0.710329, "lat": 51.508482, "delta": 23, "distance": 2349}, {"lng": -0.710501, "lat": 51.508385, "delta": 17, "distance": 2366}, {"lng": -0.710587, "lat": 51.508275, "delta": 14, "distance": 2380}, {"lng": -0.710517, "lat": 51.508168, "delta": 13, "distance": 2393}, {"lng": -0.710346, "lat": 51.507991, "delta": 23, "distance": 2416}, {"lng": -0.710276, "lat": 51.507884, "delta": 13, "distance": 2429}, {"lng": -0.710356, "lat": 51.507794, "delta": 12, "distance": 2441}, {"lng": -0.710517, "lat": 51.507814, "delta": 12, "distance": 2453}, {"lng": -0.710726, "lat": 51.507864, "delta": 16, "distance": 2469}, {"lng": -0.710823, "lat": 51.507891, "delta": 8, "distance": 2477}, {"lng": -0.710909, "lat": 51.507784, "delta": 14, "distance": 2491}, {"lng": -0.711, "lat": 51.507694, "delta": 12, "distance": 2503}, {"lng": -0.711139, "lat": 51.507637, "delta": 12, "distance": 2515}, {"lng": -0.711311, "lat": 51.507671, "delta": 13, "distance": 2528}, {"lng": -0.711644, "lat": 51.508038, "delta": 47, "distance": 2575}, {"lng": -0.711531, "lat": 51.508318, "delta": 33, "distance": 2608}, {"lng": -0.711274, "lat": 51.508559, "delta": 33, "distance": 2641}, {"lng": -0.71108, "lat": 51.508632, "delta": 16, "distance": 2657}, {"lng": -0.710785, "lat": 51.508509, "delta": 25, "distance": 2682}, {"lng": -0.710571, "lat": 51.508459, "delta": 16, "distance": 2698}, {"lng": -0.710394, "lat": 51.508502, "delta": 14, "distance": 2712}, {"lng": -0.710217, "lat": 51.508669, "delta": 23, "distance": 2735}, {"lng": -0.710367, "lat": 51.509707, "delta": 116, "distance": 2851}, {"lng": -0.711043, "lat": 51.512104, "delta": 271, "distance": 3122}, {"lng": -0.712008, "lat": 51.51587, "delta": 425, "distance": 3547}, {"lng": -0.71166, "lat": 51.515987, "delta": 28, "distance": 3575}, {"lng": -0.7113, "lat": 51.51603, "delta": 26, "distance": 3601}, {"lng": -0.710796, "lat": 51.516057, "delta": 36, "distance": 3637}, {"lng": -0.710544, "lat": 51.51606, "delta": 18, "distance": 3655}, {"lng": -0.710421, "lat": 51.51598, "delta": 13, "distance": 3668}, {"lng": -0.708779, "lat": 51.512779, "delta": 374, "distance": 4042}, {"lng": -0.708801, "lat": 51.512602, "delta": 20, "distance": 4062}, {"lng": -0.70857, "lat": 51.512151, "delta": 53, "distance": 4115}, {"lng": -0.707878, "lat": 51.510712, "delta": 168, "distance": 4283}, {"lng": -0.707899, "lat": 51.510308, "delta": 45, "distance": 4328}, {"lng": -0.708039, "lat": 51.510228, "delta": 14, "distance": 4342}, {"lng": -0.708602, "lat": 51.509891, "delta": 55, "distance": 4397}, {"lng": -0.708817, "lat": 51.509788, "delta": 19, "distance": 4416}, {"lng": -0.710115, "lat": 51.508666, "delta": 154, "distance": 4570}, {"lng": -0.710399, "lat": 51.508455, "delta": 31, "distance": 4601}, {"lng": -0.710555, "lat": 51.508342, "delta": 17, "distance": 4618}, {"lng": -0.710512, "lat": 51.508218, "delta": 15, "distance": 4633}, {"lng": -0.710265, "lat": 51.507884, "delta": 41, "distance": 4674}, {"lng": -0.710399, "lat": 51.507774, "delta": 16, "distance": 4690}, {"lng": -0.710828, "lat": 51.507898, "delta": 33, "distance": 4723}, {"lng": -0.711016, "lat": 51.507701, "delta": 26, "distance": 4749}, {"lng": -0.711198, "lat": 51.507661, "delta": 14, "distance": 4763}, {"lng": -0.711349, "lat": 51.507681, "delta": 11, "distance": 4774}, {"lng": -0.711617, "lat": 51.508051, "delta": 46, "distance": 4820}, {"lng": -0.711536, "lat": 51.508355, "delta": 35, "distance": 4855}, {"lng": -0.711306, "lat": 51.508566, "delta": 29, "distance": 4884}, {"lng": -0.711129, "lat": 51.508786, "delta": 28, "distance": 4912}, {"lng": -0.710973, "lat": 51.50934, "delta": 63, "distance": 4975}, {"lng": -0.711456, "lat": 51.509804, "delta": 62, "distance": 5037}, {"lng": -0.711429, "lat": 51.510051, "delta": 28, "distance": 5065}, {"lng": -0.711601, "lat": 51.510332, "delta": 34, "distance": 5099}]