[{"lng": 152.98104, "lat": -27.407512, "delta": 0, "distance": 0}, {"lng": 152.98156, "lat": -27.407989, "delta": 74, "distance": 74}, {"lng": 152.981882, "lat": -27.40816, "delta": 38, "distance": 112}, {"lng": 152.981989, "lat": -27.408227, "delta": 13, "distance": 125}, {"lng": 152.982043, "lat": -27.408403, "delta": 21, "distance": 146}, {"lng": 152.982332, "lat": -27.408494, "delta": 31, "distance": 177}, {"lng": 152.982574, "lat": -27.408374, "delta": 28, "distance": 205}, {"lng": 152.982906, "lat": -27.408417, "delta": 34, "distance": 239}, {"lng": 152.983282, "lat": -27.408584, "delta": 42, "distance": 281}, {"lng": 152.983496, "lat": -27.40876, "delta": 29, "distance": 310}, {"lng": 152.98369, "lat": -27.408965, "delta": 30, "distance": 340}, {"lng": 152.983663, "lat": -27.409217, "delta": 29, "distance": 369}, {"lng": 152.983647, "lat": -27.409365, "delta": 17, "distance": 386}, {"lng": 152.983888, "lat": -27.409613, "delta": 37, "distance": 423}, {"lng": 152.984242, "lat": -27.409808, "delta": 42, "distance": 465}, {"lng": 152.984532, "lat": -27.409927, "delta": 32, "distance": 497}, {"lng": 152.984832, "lat": -27.409951, "delta": 30, "distance": 527}, {"lng": 152.985127, "lat": -27.409989, "delta": 30, "distance": 557}, {"lng": 152.985331, "lat": -27.409984, "delta": 21, "distance": 578}, {"lng": 152.985792, "lat": -27.410051, "delta": 47, "distance": 625}, {"lng": 152.986377, "lat": -27.409908, "delta": 60, "distance": 685}, {"lng": 152.986629, "lat": -27.409903, "delta": 25, "distance": 710}, {"lng": 152.987128, "lat": -27.410027, "delta": 52, "distance": 762}, {"lng": 152.987616, "lat": -27.410303, "delta": 58, "distance": 820}, {"lng": 152.98789, "lat": -27.410413, "delta": 30, "distance": 850}, {"lng": 152.988099, "lat": -27.410546, "delta": 26, "distance": 876}, {"lng": 152.988298, "lat": -27.410603, "delta": 21, "distance": 897}, {"lng": 152.988491, "lat": -27.411156, "delta": 65, "distance": 962}, {"lng": 152.988609, "lat": -27.41146, "delta": 36, "distance": 998}, {"lng": 152.988786, "lat": -27.411698, "delta": 32, "distance": 1030}, {"lng": 152.988888, "lat": -27.412056, "delta": 42, "distance": 1072}, {"lng": 152.989483, "lat": -27.412998, "delta": 121, "distance": 1193}, {"lng": 152.98981, "lat": -27.41316, "delta": 37, "distance": 1230}, {"lng": 152.98996, "lat": -27.413498, "delta": 41, "distance": 1271}, {"lng": 152.990277, "lat": -27.413827, "delta": 49, "distance": 1320}, {"lng": 152.990534, "lat": -27.413932, "delta": 28, "distance": 1348}, {"lng": 152.990851, "lat": -27.413837, "delta": 34, "distance": 1382}, {"lng": 152.991286, "lat": -27.413294, "delta": 75, "distance": 1457}, {"lng": 152.991668, "lat": -27.412907, "delta": 58, "distance": 1515}, {"lng": 152.991918, "lat": -27.412675, "delta": 36, "distance": 1551}, {"lng": 152.992106, "lat": -27.412537, "delta": 25, "distance": 1576}, {"lng": 152.992144, "lat": -27.412337, "delta": 23, "distance": 1599}, {"lng": 152.992058, "lat": -27.412151, "delta": 23, "distance": 1622}, {"lng": 152.992369, "lat": -27.411951, "delta": 38, "distance": 1660}, {"lng": 152.992548, "lat": -27.412001, "delta": 19, "distance": 1679}, {"lng": 152.993184, "lat": -27.41136, "delta": 95, "distance": 1774}, {"lng": 152.993807, "lat": -27.410903, "delta": 80, "distance": 1854}, {"lng": 152.994118, "lat": -27.410746, "delta": 36, "distance": 1890}, {"lng": 152.994568, "lat": -27.410589, "delta": 48, "distance": 1938}, {"lng": 152.994735, "lat": -27.410303, "delta": 36, "distance": 1974}, {"lng": 152.994799, "lat": -27.410022, "delta": 32, "distance": 2006}, {"lng": 152.995196, "lat": -27.41006, "delta": 40, "distance": 2046}, {"lng": 152.995304, "lat": -27.410265, "delta": 26, "distance": 2072}, {"lng": 152.995759, "lat": -27.410422, "delta": 49, "distance": 2121}, {"lng": 152.996087, "lat": -27.41056, "delta": 36, "distance": 2157}, {"lng": 152.996704, "lat": -27.410941, "delta": 75, "distance": 2232}, {"lng": 152.997412, "lat": -27.411303, "delta": 81, "distance": 2313}, {"lng": 152.997556, "lat": -27.411418, "delta": 20, "distance": 2333}, {"lng": 152.997471, "lat": -27.41167, "delta": 30, "distance": 2363}, {"lng": 152.997304, "lat": -27.41197, "delta": 38, "distance": 2401}, {"lng": 152.997288, "lat": -27.412151, "delta": 21, "distance": 2422}, {"lng": 152.997519, "lat": -27.412289, "delta": 28, "distance": 2450}, {"lng": 152.997948, "lat": -27.412475, "delta": 48, "distance": 2498}, {"lng": 152.998125, "lat": -27.412663, "delta": 28, "distance": 2526}]