[{"lng": -2.105244, "lat": 53.534862, "delta": 0, "distance": 0}, {"lng": -2.101972, "lat": 53.533899, "delta": 242, "distance": 242}, {"lng": -2.101715, "lat": 53.534097, "delta": 28, "distance": 270}, {"lng": -2.102079, "lat": 53.534454000000004, "delta": 47, "distance": 317}, {"lng": -2.102294, "lat": 53.534499000000004, "delta": 16, "distance": 333}, {"lng": -2.1027230000000006, "lat": 53.534639, "delta": 33, "distance": 366}, {"lng": -2.1030130000000002, "lat": 53.534652, "delta": 20, "distance": 386}, {"lng": -2.103163, "lat": 53.534563, "delta": 15, "distance": 401}, {"lng": -2.103828, "lat": 53.534792, "delta": 51, "distance": 452}, {"lng": -2.104365, "lat": 53.534907, "delta": 38, "distance": 490}, {"lng": -2.104923, "lat": 53.535258, "delta": 54, "distance": 544}, {"lng": -2.10577, "lat": 53.535372, "delta": 58, "distance": 602}, {"lng": -2.106092, "lat": 53.535347, "delta": 22, "distance": 624}, {"lng": -2.106714, "lat": 53.535608, "delta": 51, "distance": 675}, {"lng": -2.107358, "lat": 53.535602, "delta": 43, "distance": 718}, {"lng": -2.108678, "lat": 53.534499000000004, "delta": 151, "distance": 869}, {"lng": -2.108388, "lat": 53.533523, "delta": 111, "distance": 980}, {"lng": -2.107841, "lat": 53.533179, "delta": 53, "distance": 1033}, {"lng": -2.107165, "lat": 53.532898, "delta": 55, "distance": 1088}, {"lng": -2.105427, "lat": 53.532363, "delta": 130, "distance": 1218}, {"lng": -2.104751, "lat": 53.53310900000001, "delta": 95, "distance": 1313}, {"lng": -2.103796, "lat": 53.53293600000001, "delta": 66, "distance": 1379}, {"lng": -2.102745, "lat": 53.532834, "delta": 71, "distance": 1450}, {"lng": -2.101511, "lat": 53.532943, "delta": 83, "distance": 1533}, {"lng": -2.10061, "lat": 53.533089, "delta": 62, "distance": 1595}, {"lng": -2.100191, "lat": 53.533249, "delta": 33, "distance": 1628}, {"lng": -2.098882, "lat": 53.533969, "delta": 118, "distance": 1746}, {"lng": -2.100019, "lat": 53.534116, "delta": 77, "distance": 1823}, {"lng": -2.10121, "lat": 53.534199, "delta": 80, "distance": 1903}, {"lng": -2.101833, "lat": 53.533734, "delta": 67, "distance": 1970}, {"lng": -2.106661, "lat": 53.535187, "delta": 358, "distance": 2328}, {"lng": -2.106671, "lat": 53.535347, "delta": 18, "distance": 2346}, {"lng": -2.106768, "lat": 53.535455, "delta": 14, "distance": 2360}, {"lng": -2.107004, "lat": 53.5355, "delta": 17, "distance": 2377}, {"lng": -2.107176, "lat": 53.535468, "delta": 12, "distance": 2389}, {"lng": -2.107326, "lat": 53.535385, "delta": 14, "distance": 2403}, {"lng": -2.10797, "lat": 53.534881, "delta": 71, "distance": 2474}, {"lng": -2.108345, "lat": 53.534467, "delta": 53, "distance": 2527}, {"lng": -2.108291, "lat": 53.534078, "delta": 44, "distance": 2571}, {"lng": -2.1081090000000002, "lat": 53.533644, "delta": 50, "distance": 2621}, {"lng": -2.107873, "lat": 53.53344, "delta": 28, "distance": 2649}, {"lng": -2.107637, "lat": 53.5333, "delta": 23, "distance": 2672}, {"lng": -2.10724, "lat": 53.533089, "delta": 36, "distance": 2708}, {"lng": -2.106789, "lat": 53.532898, "delta": 37, "distance": 2745}, {"lng": -2.105588, "lat": 53.532535, "delta": 90, "distance": 2835}, {"lng": -2.104901, "lat": 53.533319, "delta": 99, "distance": 2934}, {"lng": -2.103742, "lat": 53.533051, "delta": 83, "distance": 3017}, {"lng": -2.102755, "lat": 53.532962, "delta": 66, "distance": 3083}, {"lng": -2.102079, "lat": 53.533051, "delta": 46, "distance": 3129}, {"lng": -2.101597, "lat": 53.533083, "delta": 33, "distance": 3162}, {"lng": -2.100738, "lat": 53.533211, "delta": 59, "distance": 3221}, {"lng": -2.0999340000000006, "lat": 53.533529, "delta": 64, "distance": 3285}, {"lng": -2.099301, "lat": 53.533855, "delta": 56, "distance": 3341}, {"lng": -2.10017, "lat": 53.533982, "delta": 60, "distance": 3401}, {"lng": -2.101092, "lat": 53.534052, "delta": 62, "distance": 3463}, {"lng": -2.101822, "lat": 53.533638, "delta": 67, "distance": 3530}, {"lng": -2.105545, "lat": 53.534735, "delta": 275, "distance": 3805}, {"lng": -2.106864, "lat": 53.535143, "delta": 99, "distance": 3904}, {"lng": -2.107165, "lat": 53.535309, "delta": 28, "distance": 3932}, {"lng": -2.107712, "lat": 53.534894, "delta": 59, "distance": 3991}, {"lng": -2.1080980000000005, "lat": 53.534454000000004, "delta": 56, "distance": 4047}, {"lng": -2.107884, "lat": 53.533689, "delta": 87, "distance": 4134}, {"lng": -2.106897, "lat": 53.533083, "delta": 94, "distance": 4228}, {"lng": -2.105609, "lat": 53.532701, "delta": 96, "distance": 4324}, {"lng": -2.105019, "lat": 53.533504, "delta": 98, "distance": 4422}, {"lng": -2.10371, "lat": 53.533211, "delta": 93, "distance": 4515}, {"lng": -2.102691, "lat": 53.533134, "delta": 68, "distance": 4583}, {"lng": -2.101661, "lat": 53.533179, "delta": 69, "distance": 4652}, {"lng": -2.100567, "lat": 53.533415000000005, "delta": 77, "distance": 4729}, {"lng": -2.099719, "lat": 53.533804, "delta": 71, "distance": 4800}, {"lng": -2.101071, "lat": 53.533938, "delta": 91, "distance": 4891}, {"lng": -2.101725, "lat": 53.533517, "delta": 64, "distance": 4955}, {"lng": -2.104139, "lat": 53.534186, "delta": 177, "distance": 5132}]