[{"lng": -1.6178441, "lat": 54.9852664, "delta": 0, "distance": 0}, {"lng": -1.6180372, "lat": 54.9852171, "delta": 14, "distance": 14}, {"lng": -1.6181445, "lat": 54.985143300000004, "delta": 11, "distance": 25}, {"lng": -1.618005, "lat": 54.9838966, "delta": 139, "distance": 164}, {"lng": -1.6180694000000002, "lat": 54.9838235, "delta": 10, "distance": 174}, {"lng": -1.619314, "lat": 54.9838382, "delta": 80, "distance": 254}, {"lng": -1.6194454, "lat": 54.9838197, "delta": 9, "distance": 263}, {"lng": -1.6195822, "lat": 54.9837581, "delta": 12, "distance": 275}, {"lng": -1.6196667, "lat": 54.983675, "delta": 11, "distance": 286}, {"lng": -1.6197404, "lat": 54.9836566, "delta": 6, "distance": 292}, {"lng": -1.6226238, "lat": 54.9861113, "delta": 330, "distance": 622}, {"lng": -1.6181418, "lat": 54.985091, "delta": 308, "distance": 930}]