[{"lng": -1.032893, "lat": 50.888463, "delta": 0, "distance": 0}, {"lng": -1.032589, "lat": 50.888408, "delta": 23, "distance": 23}, {"lng": -1.03287, "lat": 50.88838200000001, "delta": 20, "distance": 43}, {"lng": -1.032589, "lat": 50.888408, "delta": 20, "distance": 63}, {"lng": -1.031789, "lat": 50.888269, "delta": 59, "distance": 122}, {"lng": -1.031655, "lat": 50.888562, "delta": 34, "distance": 156}, {"lng": -1.031411, "lat": 50.888776, "delta": 30, "distance": 186}, {"lng": -1.031116, "lat": 50.888962, "delta": 30, "distance": 216}, {"lng": -1.030969, "lat": 50.889052, "delta": 15, "distance": 231}, {"lng": -1.030931, "lat": 50.889142, "delta": 11, "distance": 242}, {"lng": -1.030955, "lat": 50.889228, "delta": 10, "distance": 252}, {"lng": -1.031063, "lat": 50.889318, "delta": 13, "distance": 265}, {"lng": -1.031197, "lat": 50.889414, "delta": 15, "distance": 280}, {"lng": -1.031352, "lat": 50.889534, "delta": 18, "distance": 298}, {"lng": -1.031583, "lat": 50.889636, "delta": 20, "distance": 318}, {"lng": -1.031768, "lat": 50.889651, "delta": 14, "distance": 332}, {"lng": -1.031991, "lat": 50.889648, "delta": 16, "distance": 348}, {"lng": -1.032168, "lat": 50.889584, "delta": 15, "distance": 363}, {"lng": -1.032533, "lat": 50.88933, "delta": 39, "distance": 402}, {"lng": -1.032868, "lat": 50.889084, "delta": 37, "distance": 439}, {"lng": -1.033144, "lat": 50.88881, "delta": 37, "distance": 476}, {"lng": -1.033216, "lat": 50.888682, "delta": 16, "distance": 492}, {"lng": -1.033182, "lat": 50.88857, "delta": 13, "distance": 505}, {"lng": -1.03305, "lat": 50.888463, "delta": 16, "distance": 521}, {"lng": -1.0333130000000001, "lat": 50.888333, "delta": 24, "distance": 545}, {"lng": -1.033659, "lat": 50.888137, "delta": 33, "distance": 578}, {"lng": -1.033761, "lat": 50.888071, "delta": 11, "distance": 589}, {"lng": -1.033825, "lat": 50.887946, "delta": 15, "distance": 604}, {"lng": -1.033833, "lat": 50.88777, "delta": 20, "distance": 624}, {"lng": -1.03382, "lat": 50.8876, "delta": 19, "distance": 643}, {"lng": -1.033874, "lat": 50.887419, "delta": 21, "distance": 664}, {"lng": -1.033949, "lat": 50.887179, "delta": 28, "distance": 692}, {"lng": -1.033965, "lat": 50.88703, "delta": 17, "distance": 709}, {"lng": -1.033957, "lat": 50.88692, "delta": 13, "distance": 722}, {"lng": -1.033876, "lat": 50.886883, "delta": 8, "distance": 730}, {"lng": -1.033525, "lat": 50.886805, "delta": 27, "distance": 757}, {"lng": -1.03323, "lat": 50.886717, "delta": 23, "distance": 780}, {"lng": -1.032948, "lat": 50.886617, "delta": 23, "distance": 803}, {"lng": -1.032736, "lat": 50.886538, "delta": 18, "distance": 821}, {"lng": -1.032524, "lat": 50.886472, "delta": 17, "distance": 838}, {"lng": -1.032417, "lat": 50.88645, "delta": 8, "distance": 846}, {"lng": -1.032339, "lat": 50.88655, "delta": 13, "distance": 859}, {"lng": -1.032133, "lat": 50.886839, "delta": 36, "distance": 895}, {"lng": -1.031929, "lat": 50.887118, "delta": 35, "distance": 930}, {"lng": -1.031835, "lat": 50.887294, "delta": 21, "distance": 951}, {"lng": -1.031789, "lat": 50.887375, "delta": 10, "distance": 961}, {"lng": -1.031851, "lat": 50.887558, "delta": 21, "distance": 982}, {"lng": -1.031765, "lat": 50.887732, "delta": 21, "distance": 1003}, {"lng": -1.031811, "lat": 50.887765, "delta": 5, "distance": 1008}, {"lng": -1.031832, "lat": 50.887826, "delta": 7, "distance": 1015}, {"lng": -1.031725, "lat": 50.88799, "delta": 20, "distance": 1035}, {"lng": -1.031658, "lat": 50.88811, "delta": 15, "distance": 1050}, {"lng": -1.031693, "lat": 50.88825200000001, "delta": 16, "distance": 1066}, {"lng": -1.031792, "lat": 50.888267, "delta": 8, "distance": 1074}]