[{"lng": 144.634538, "lat": -37.881664, "delta": 0, "distance": 0}, {"lng": 144.636404, "lat": -37.88224, "delta": 176, "distance": 176}, {"lng": 144.635224, "lat": -37.883161, "delta": 146, "distance": 322}, {"lng": 144.634892, "lat": -37.883906, "delta": 88, "distance": 410}, {"lng": 144.634784, "lat": -37.884253, "delta": 40, "distance": 450}, {"lng": 144.634902, "lat": -37.884448000000006, "delta": 25, "distance": 475}, {"lng": 144.635117, "lat": -37.884566, "delta": 23, "distance": 498}, {"lng": 144.635589, "lat": -37.88455, "delta": 42, "distance": 540}, {"lng": 144.63590000000002, "lat": -37.884558, "delta": 28, "distance": 568}, {"lng": 144.63663, "lat": -37.884905, "delta": 75, "distance": 643}, {"lng": 144.63707, "lat": -37.885015, "delta": 41, "distance": 684}, {"lng": 144.637767, "lat": -37.884727, "delta": 70, "distance": 754}, {"lng": 144.638432, "lat": -37.88414300000001, "delta": 88, "distance": 842}, {"lng": 144.638754, "lat": -37.883881, "delta": 41, "distance": 883}, {"lng": 144.63913, "lat": -37.883136, "delta": 90, "distance": 973}, {"lng": 144.639452, "lat": -37.88228000000001, "delta": 100, "distance": 1073}, {"lng": 144.639441, "lat": -37.882043, "delta": 27, "distance": 1100}, {"lng": 144.639612, "lat": -37.882026, "delta": 16, "distance": 1116}, {"lng": 144.639827, "lat": -37.882543000000005, "delta": 61, "distance": 1177}, {"lng": 144.640074, "lat": -37.883025, "delta": 58, "distance": 1235}, {"lng": 144.640074, "lat": -37.883804, "delta": 87, "distance": 1322}, {"lng": 144.640342, "lat": -37.884761, "delta": 109, "distance": 1431}, {"lng": 144.64105, "lat": -37.88659, "delta": 213, "distance": 1644}, {"lng": 144.641507, "lat": -37.887317, "delta": 91, "distance": 1735}, {"lng": 144.641876, "lat": -37.887581, "delta": 44, "distance": 1779}, {"lng": 144.641951, "lat": -37.887937, "delta": 41, "distance": 1820}, {"lng": 144.642037, "lat": -37.888123, "delta": 23, "distance": 1843}, {"lng": 144.642144, "lat": -37.88847400000001, "delta": 41, "distance": 1884}, {"lng": 144.642525, "lat": -37.888982, "delta": 66, "distance": 1950}, {"lng": 144.642767, "lat": -37.88944, "delta": 56, "distance": 2006}, {"lng": 144.642997, "lat": -37.889842, "delta": 50, "distance": 2056}, {"lng": 144.64316400000004, "lat": -37.890164, "delta": 39, "distance": 2095}, {"lng": 144.643207, "lat": -37.890303, "delta": 16, "distance": 2111}, {"lng": 144.643212, "lat": -37.890532, "delta": 26, "distance": 2137}, {"lng": 144.643233, "lat": -37.890722, "delta": 22, "distance": 2159}, {"lng": 144.643384, "lat": -37.891006, "delta": 35, "distance": 2194}, {"lng": 144.643502, "lat": -37.891192, "delta": 24, "distance": 2218}, {"lng": 144.643931, "lat": -37.891586, "delta": 58, "distance": 2276}, {"lng": 144.644344, "lat": -37.891853, "delta": 47, "distance": 2323}, {"lng": 144.644473, "lat": -37.891891, "delta": 13, "distance": 2336}, {"lng": 144.644929, "lat": -37.892022, "delta": 43, "distance": 2379}, {"lng": 144.645165, "lat": -37.892005, "delta": 21, "distance": 2400}, {"lng": 144.64546500000003, "lat": -37.891933, "delta": 28, "distance": 2428}, {"lng": 144.645631, "lat": -37.891908, "delta": 15, "distance": 2443}, {"lng": 144.645894, "lat": -37.891903, "delta": 24, "distance": 2467}, {"lng": 144.646291, "lat": -37.891971, "delta": 36, "distance": 2503}, {"lng": 144.646661, "lat": -37.892073, "delta": 35, "distance": 2538}, {"lng": 144.646844, "lat": -37.892102, "delta": 17, "distance": 2555}, {"lng": 144.64701, "lat": -37.892094, "delta": 15, "distance": 2570}, {"lng": 144.647202, "lat": -37.892086, "delta": 17, "distance": 2587}]