[{"lng": 15.135083, "lat": 51.616711, "delta": 0, "distance": 0}, {"lng": 15.135813, "lat": 51.615512, "delta": 143, "distance": 143}, {"lng": 15.135942, "lat": 51.615085, "delta": 49, "distance": 192}, {"lng": 15.135813, "lat": 51.613886, "delta": 134, "distance": 326}, {"lng": 15.136027, "lat": 51.613193, "delta": 79, "distance": 405}, {"lng": 15.136199, "lat": 51.612154, "delta": 117, "distance": 522}, {"lng": 15.135341, "lat": 51.611115, "delta": 130, "distance": 652}, {"lng": 15.134697, "lat": 51.610422, "delta": 89, "distance": 741}, {"lng": 15.134697, "lat": 51.610022, "delta": 45, "distance": 786}, {"lng": 15.135126, "lat": 51.609942, "delta": 31, "distance": 817}, {"lng": 15.136757, "lat": 51.610688, "delta": 140, "distance": 957}, {"lng": 15.13813, "lat": 51.611035, "delta": 103, "distance": 1060}, {"lng": 15.139031, "lat": 51.611168, "delta": 64, "distance": 1124}, {"lng": 15.141864, "lat": 51.60717, "delta": 486, "distance": 1610}, {"lng": 15.142593, "lat": 51.607037, "delta": 53, "distance": 1663}, {"lng": 15.143838, "lat": 51.604665, "delta": 278, "distance": 1941}, {"lng": 15.147443, "lat": 51.608023, "delta": 449, "distance": 2390}, {"lng": 15.149803, "lat": 51.609542, "delta": 235, "distance": 2625}, {"lng": 15.151091, "lat": 51.610768, "delta": 163, "distance": 2788}, {"lng": 15.151906, "lat": 51.611434, "delta": 94, "distance": 2882}, {"lng": 15.152464, "lat": 51.611621, "delta": 44, "distance": 2926}, {"lng": 15.154696, "lat": 51.612874, "delta": 208, "distance": 3134}, {"lng": 15.15388, "lat": 51.6129, "delta": 57, "distance": 3191}, {"lng": 15.153108, "lat": 51.613167, "delta": 62, "distance": 3253}, {"lng": 15.151134, "lat": 51.613406, "delta": 139, "distance": 3392}, {"lng": 15.150876, "lat": 51.613646, "delta": 33, "distance": 3425}, {"lng": 15.149374, "lat": 51.61386, "delta": 107, "distance": 3532}, {"lng": 15.148258, "lat": 51.61378, "delta": 78, "distance": 3610}, {"lng": 15.14504, "lat": 51.612794, "delta": 248, "distance": 3858}, {"lng": 15.144224, "lat": 51.612794, "delta": 57, "distance": 3915}, {"lng": 15.142593, "lat": 51.612234, "delta": 129, "distance": 4044}, {"lng": 15.140147, "lat": 51.614286, "delta": 284, "distance": 4328}, {"lng": 15.140362, "lat": 51.615245, "delta": 108, "distance": 4436}, {"lng": 15.141048, "lat": 51.616205, "delta": 117, "distance": 4553}, {"lng": 15.141006, "lat": 51.616418, "delta": 24, "distance": 4577}, {"lng": 15.139504, "lat": 51.616231, "delta": 106, "distance": 4683}, {"lng": 15.138087, "lat": 51.616178, "delta": 99, "distance": 4782}, {"lng": 15.137444, "lat": 51.616125, "delta": 45, "distance": 4827}, {"lng": 15.13577, "lat": 51.615725, "delta": 124, "distance": 4951}, {"lng": 15.135984, "lat": 51.616311, "delta": 67, "distance": 5018}]